commitzilla/__init__.py
commitzilla/characters.py
commitzilla/config.py
commitzilla/cz_characters.json
commitzilla/main.py
commitzilla/prepare-commit-msg.py
commitzilla-0.2.1.dist-info/METADATA
commitzilla-0.2.1.dist-info/WHEEL
commitzilla-0.2.1.dist-info/entry_points.txt
commitzilla-0.2.1.dist-info/RECORD
