Metadata-Version: 2.1
Name: commitzilla
Version: 0.2.1
Summary: Make your commit messages helpful, for once
Author: Scuffi
Author-email: grawlixpvp@gmail.com
Requires-Python: >=3.9,<4.0
Classifier: Programming Language :: Python :: 3
Classifier: Programming Language :: Python :: 3.9
Classifier: Programming Language :: Python :: 3.10
Classifier: Programming Language :: Python :: 3.11
Classifier: Programming Language :: Python :: 3.12
Classifier: Programming Language :: Python :: 3.13
Requires-Dist: keyring (>=25.5.0,<26.0.0)
Requires-Dist: questionary (>=2.0.1,<3.0.0)
Requires-Dist: typer (>=0.12.5,<0.13.0)
